graph/__init__.py
graph/constants.py
graph/coordinate.py
graph/djikstra.py
aoc_py_utils-0.0.1.dist-info/METADATA
aoc_py_utils-0.0.1.dist-info/WHEEL
aoc_py_utils-0.0.1.dist-info/top_level.txt
aoc_py_utils-0.0.1.dist-info/RECORD
